include_pycharm_modules/__init__.py
include_pycharm_modules/source_folder.py
include_pycharm_modules-0.0.3.dist-info/WHEEL
include_pycharm_modules-0.0.3.dist-info/METADATA
include_pycharm_modules-0.0.3.dist-info/RECORD
