Metadata-Version: 2.1
Name: include-pycharm-modules
Version: 0.0.3
Summary: Adds any pycharm source folder to the python module search path so you can import them as if they were installed
Home-page: https://github.com/KIC/include-pycharm-modules
Author: KIC
Author-email: 
Requires-Python: >= 3.7
Classifier: License :: OSI Approved :: MIT License
Classifier: Development Status :: 2 - Pre-Alpha
Requires-Dist: beautifulsoup4
